[{"__type__":"cc.SpriteFrame","content":{"name":"angry4","texture":"2bbqioDsJOuYATG629P77S","rect":[1163,650,112,116],"offset":[0,0],"originalSize":[112,116]}},{"__type__":"cc.SpriteFrame","content":{"name":"angry6","texture":"2bbqioDsJOuYATG629P77S","rect":[1344,268,112,116],"offset":[0,0],"originalSize":[112,116]}},{"__type__":"cc.SpriteFrame","content":{"name":"angry3","texture":"2bbqioDsJOuYATG629P77S","rect":[1151,804,112,116],"offset":[0,0],"originalSize":[112,116]}},{"__type__":"cc.SpriteFrame","content":{"name":"angry7","texture":"2bbqioDsJOuYATG629P77S","rect":[1377,116,112,116],"offset":[0,0],"originalSize":[112,116]}},{"__type__":"cc.SpriteFrame","content":{"name":"angry5","texture":"2bbqioDsJOuYATG629P77S","rect":[1252,447,112,116],"offset":[0,0],"originalSize":[112,116]}},{"__type__":"cc.SpriteFrame","content":{"name":"angry0","texture":"2bbqioDsJOuYATG629P77S","rect":[1232,331,112,116],"offset":[0,0],"originalSize":[112,116]}},{"__type__":"cc.SpriteFrame","content":{"name":"angry1","texture":"2bbqioDsJOuYATG629P77S","rect":[1265,152,112,116],"offset":[0,0],"originalSize":[112,116]}},{"__type__":"cc.AnimationClip","_name":"angry","_duration":1.3333333333333333,"sample":6,"wrapMode":2,"curveData":{"comps":{"cc.Sprite":{"spriteFrame":[{"frame":0,"value":{"__uuid__":"8f4iTlZA1Kh5m2+h4mFxO/"}},{"frame":0.16666666666666666,"value":{"__uuid__":"e8hkiqySFMTKBxnvjqlaJi"}},{"frame":0.3333333333333333,"value":{"__uuid__":"e8hkiqySFMTKBxnvjqlaJi"}},{"frame":0.5,"value":{"__uuid__":"43zxlLlR9B0qv4SwBZb8mc"}},{"frame":0.6666666666666666,"value":{"__uuid__":"0caLRkKxBNZKAl6TlShFFh"}},{"frame":0.8333333333333334,"value":{"__uuid__":"74EcCdL4lCAp16EQFJNRPU"}},{"frame":1,"value":{"__uuid__":"1ciAhsi9xEgLZRgqcSc/B5"}},{"frame":1.1666666666666667,"value":{"__uuid__":"57SmuHQPVGf5vUXezS6GE4"}}]}}}}]